digital_lock.v
module digital_lock (
    input  wire        clk,
    input  wire        rst,
    input  wire [3:0]  key_in,
    input  wire        key_valid,
    output reg  [3:0]  seg_digit,
    output reg         led_unlock,
    output reg         led_error,
    output reg         led_locked,
    output reg  [1:0]  error_count
);

// ========== Configurable password digits ==========
parameter DIGIT0 = 4'd1;
parameter DIGIT1 = 4'd2;
parameter DIGIT2 = 4'd3;
parameter DIGIT3 = 4'd4;

// ========== State encoding ==========
localparam IDLE      = 3'd0;
localparam INPUT_1   = 3'd1; 
localparam INPUT_2   = 3'd2; 
localparam INPUT_3   = 3'd3; 
localparam CHECK     = 3'd4; 
localparam UNLOCKED  = 3'd5; 
localparam ERROR     = 3'd6; 
localparam LOCKED    = 3'd7; 

// State registers
reg [2:0] state, next_state;

// Storage for entered digits
reg [3:0] d0, d1, d2, d3;

// ====== 1) State register (clocked) ======
always @(posedge clk or posedge rst) begin
    if (rst)
        state <= IDLE;
    else
        state <= next_state;
end

// ====== 2) Next-state combinational logic ======
always @(*) begin
    next_state = state; // Default: stay in current state
    case (state)
        IDLE: begin
            if (key_valid && key_in <= 4'd9)
                next_state = INPUT_1;
            else
                next_state = IDLE;
        end
        INPUT_1: begin
            if (key_valid && key_in <= 4'd9)
                next_state = INPUT_2;
            else
                next_state = INPUT_1;
        end
        INPUT_2: begin
            if (key_valid && key_in <= 4'd9)
                next_state = INPUT_3;
            else
                next_state = INPUT_2;
        end
        INPUT_3: begin
            if (key_valid && key_in <= 4'd9)
                next_state = CHECK;
            else
                next_state = INPUT_3;
        end
        CHECK: begin
            if ( (d0 == DIGIT0) && (d1 == DIGIT1) && (d2 == DIGIT2) && (d3 == DIGIT3) )
                next_state = UNLOCKED;
            else
                next_state = ERROR;
        end
        ERROR: begin
            // Transition to IDLE or LOCKED in next cycle
            if (error_count >= 2'd2) // This is the 3rd error (0, 1, 2)
                next_state = LOCKED;
            else
                next_state = IDLE;
        end
        UNLOCKED: begin
            // Wait for rst
            next_state = UNLOCKED;
        end
        LOCKED: begin
            // Wait for rst
            next_state = LOCKED;
        end
        default: next_state = IDLE;
    endcase
end

// ====== 3) Internal data & Error counter (clocked) ======
always @(posedge clk or posedge rst) begin
    if (rst) begin
        d0 <= 4'd0;
        d1 <= 4'd0;
        d2 <= 4'd0;
        d3 <= 4'd0;
        error_count <= 2'd0;
    end else begin
        case (state)
            IDLE: begin
                if (key_valid && key_in <= 4'd9)
                    d0 <= key_in;
            end
            INPUT_1: begin
                if (key_valid && key_in <= 4'd9)
                    d1 <= key_in;
            end
            INPUT_2: begin
                if (key_valid && key_in <= 4'd9)
                    d2 <= key_in;
            end
            INPUT_3: begin
                if (key_valid && key_in <= 4'd9)
                    d3 <= key_in;
            end
            CHECK: begin
                // If correct, reset error count. If wrong, ERROR state handles increment.
                if ( (d0 == DIGIT0) && (d1 == DIGIT1) && (d2 == DIGIT2) && (d3 == DIGIT3) )
                    error_count <= 2'd0;
            end
            ERROR: begin
                if (error_count < 2'd3)
                    error_count <= error_count + 2'd1;
            end
            default: ;
        endcase
    end
end

// ====== 4) Output logic (combinational or sequential) ======
// Using sequential for glitch-free outputs and following Verilog-2001 style
always @(posedge clk or posedge rst) begin
    if (rst) begin
        seg_digit    <= 4'd0;
        led_unlock   <= 1'b0;
        led_error    <= 1'b0;
        led_locked   <= 1'b0;
    end else begin
        // Default values
        led_error <= 1'b0;
        
        case (next_state) // Lookahead to next_state for faster output response if needed, 
                          // or use current state. The prompt says "一拍" for error.
                          // Let's use current state to be safe and match "一拍" exactly.
            default: ; 
        endcase

        // Using current state for standard Moore FSM outputs
        case (state)
            IDLE: begin
                seg_digit    <= 4'd0;
                led_unlock   <= 1'b0;
                led_locked   <= 1'b0;
            end
            INPUT_1: begin
                seg_digit <= 4'd1;
            end
            INPUT_2: begin
                seg_digit <= 4'd2;
            end
            INPUT_3: begin
                seg_digit <= 4'd3;
            end
            CHECK: begin
                seg_digit <= 4'd4;
            end
            UNLOCKED: begin
                led_unlock <= 1'b1;
            end
            ERROR: begin
                led_error <= 1'b1;
            end
            LOCKED: begin
                led_locked <= 1'b1;
            end
        endcase
    end
end

endmodule

tb_digital_lock.v
`timescale 1ns/1ps

module tb_digital_lock;

// 信號宣告
reg clk;
reg rst;
reg [3:0] key_in;
reg key_valid;

wire [3:0] seg_digit;
wire led_unlock;
wire led_error;
wire led_locked;
wire [1:0] error_count;

// DUT 實體化
digital_lock uut (
    .clk(clk),
    .rst(rst),
    .key_in(key_in),
    .key_valid(key_valid),
    .seg_digit(seg_digit),
    .led_unlock(led_unlock),
    .led_error(led_error),
    .led_locked(led_locked),
    .error_count(error_count)
);

// 時脈產生 (100MHz)
initial clk = 0;
always #5 clk = ~clk;

// 模擬按鍵輸入的 task
task press_key;
    input [3:0] digit;
    begin
        @(posedge clk);
        key_in = digit;
        key_valid = 1'b1;
        @(posedge clk);
        key_valid = 1'b0;
        #20; // 模擬去彈跳間隔
    end
endtask

// 輸入四位密碼的 task
task enter_password;
    input [3:0] d0, d1, d2, d3;
    begin
        press_key(d0);
        press_key(d1);
        press_key(d2);
        press_key(d3);
    end
endtask

// 測試流程
initial begin
    $dumpfile("wave.vcd");
    $dumpvars(0, tb_digital_lock);

    // 初始狀態
    rst = 1; key_in = 0; key_valid = 0;
    #25; rst = 0;
    #20;

    // --- 測試 1: 正確密碼測試 (1->2->3->4) ---
    $display("=== Correct Password (1-2-3-4) ===");
    enter_password(4'd1, 4'd2, 4'd3, 4'd4);
    #20;
    $display("Time=%t | unlock=%b, error=%b, locked=%b, digit=%d", $time, led_unlock, led_error, led_locked, seg_digit);
    
    if (led_unlock) $display(">>> SUCCESS: System Unlocked");
    else $display(">>> ERROR: System failed to unlock");

    // --- 測試 5: 中途重置測試 (輸入一半時按 rst) ---
    $display("\n>>> Resetting system...");
    rst = 1; #20; rst = 0; #20;
    $display("=== Scenario 5: Mid-input Reset ===");
    press_key(4'd1);
    press_key(4'd2);
    $display("Before reset: seg_digit=%d", seg_digit);
    rst = 1; #20; rst = 0; #20;
    $display("After reset:  seg_digit=%d", seg_digit);

    if (seg_digit == 0) $display(">>> SUCCESS: seg_digit reset to 0");
    else $display(">>> ERROR: seg_digit not reset");

    // --- 測試 2: 單次錯誤測試 (1->2->3->5) ---
    $display("\n=== Scenario 2: Single Error (1-2-3-5) ===");
    enter_password(4'd1, 4'd2, 4'd3, 4'd5);
    #5;
    $display("Time=%t | unlock=%b, error=%b, locked=%b, count=%d", $time, led_unlock, led_error, led_locked, error_count);
    if (error_count == 1) $display(">>> SUCCESS: error_count incremented to 1");
    else $display(">>> ERROR: error_count is %d", error_count);

    // --- 測試 3: 三次錯誤鎖定測試 ---
    $display("\n=== Scenario 3: Three Errors Lockout ===");
    // 目前已經有 1 次錯誤 (1-2-3-5)
    // 第 2 次錯誤
    $display("Entering 2nd wrong password...");
    enter_password(4'd0, 4'd0, 4'd0, 4'd0);
    #20;
    // 第 3 次錯誤
    $display("Entering 3rd wrong password...");
    enter_password(4'd9, 4'd9, 4'd9, 4'd9);
    #20;
    $display("Time=%t | unlock=%b, error=%b, locked=%b, count=%d", $time, led_unlock, led_error, led_locked, error_count);
    if (led_locked) $display(">>> SUCCESS: System Locked");
    else $display(">>> ERROR: System not locked");

    // --- 測試 4: 鎖定後重置測試 ---
    $display("\n=== Scenario 4: Reset after Locked ===");
    $display("Trying to enter key while locked...");
    press_key(4'd1);
    if (seg_digit == 0) $display("Key ignored as expected");
    
    $display("Resetting...");
    rst = 1; #20; rst = 0; #20;
    $display("After reset: locked=%b, count=%d, digit=%d", led_locked, error_count, seg_digit);
    
    $display("Entering correct password after reset...");
    enter_password(4'd1, 4'd2, 4'd3, 4'd4);
    #20;
    $display("Time=%t | unlock=%b, error=%b, locked=%b, count=%d", $time, led_unlock, led_error, led_locked, error_count);
    if (led_unlock) $display(">>> SUCCESS: System Unlocked after reset");
    else $display(">>> ERROR: System failed to unlock after reset");

    #100;
    $finish;
end

endmodule

wave.vcd
$date
	Tue May 26 12:13:12 2026
$end
$version
	Icarus Verilog
$end
$timescale
	1ps
$end
$scope module tb_digital_lock $end
$var wire 4 ! seg_digit [3:0] $end
$var wire 1 " led_unlock $end
$var wire 1 # led_locked $end
$var wire 1 $ led_error $end
$var wire 2 % error_count [1:0] $end
$var reg 1 & clk $end
$var reg 4 ' key_in [3:0] $end
$var reg 1 ( key_valid $end
$var reg 1 ) rst $end
$scope module uut $end
$var wire 1 & clk $end
$var wire 4 * key_in [3:0] $end
$var wire 1 ( key_valid $end
$var wire 1 ) rst $end
$var parameter 3 + CHECK $end
$var parameter 4 , DIGIT0 $end
$var parameter 4 - DIGIT1 $end
$var parameter 4 . DIGIT2 $end
$var parameter 4 / DIGIT3 $end
$var parameter 3 0 ERROR $end
$var parameter 3 1 IDLE $end
$var parameter 3 2 INPUT_1 $end
$var parameter 3 3 INPUT_2 $end
$var parameter 3 4 INPUT_3 $end
$var parameter 3 5 LOCKED $end
$var parameter 3 6 UNLOCKED $end
$var reg 4 7 d0 [3:0] $end
$var reg 4 8 d1 [3:0] $end
$var reg 4 9 d2 [3:0] $end
$var reg 4 : d3 [3:0] $end
$var reg 2 ; error_count [1:0] $end
$var reg 1 $ led_error $end
$var reg 1 # led_locked $end
$var reg 1 " led_unlock $end
$var reg 3 < next_state [2:0] $end
$var reg 4 = seg_digit [3:0] $end
$var reg 3 > state [2:0] $end
$upscope $end
$scope task enter_password $end
$var reg 4 ? d0 [3:0] $end
$var reg 4 @ d1 [3:0] $end
$var reg 4 A d2 [3:0] $end
$var reg 4 B d3 [3:0] $end
$upscope $end
$scope task press_key $end
$var reg 4 C digit [3:0] $end
$upscope $end
$upscope $end
$enddefinitions $end
$comment Show the parameter values. $end
$dumpall
b101 6
b111 5
b11 4
b10 3
b1 2
b0 1
b110 0
b100 /
b11 .
b10 -
b1 ,
b100 +
$end
#0
$dumpvars
bx C
bx B
bx A
bx @
bx ?
b0 >
b0 =
b0 <
b0 ;
b0 :
b0 9
b0 8
b0 7
b0 *
1)
0(
b0 '
0&
b0 %
0$
0#
0"
b0 !
$end
#5000
1&
#10000
0&
#15000
1&
#20000
0&
#25000
1&
0)
#30000
0&
#35000
1&
#40000
0&
#45000
b1 7
b1 <
1(
b1 '
b1 *
1&
b1 C
b100 B
b11 A
b10 @
b1 ?
#50000
0&
#55000
b1 >
b1 <
0(
1&
#60000
0&
#65000
b1 !
b1 =
1&
#70000
0&
#75000
b10 8
b10 <
1(
b10 '
b10 *
1&
b10 C
#80000
0&
#85000
b10 >
b10 <
0(
1&
#90000
0&
#95000
b10 !
b10 =
1&
#100000
0&
#105000
b11 9
b11 <
1(
b11 '
b11 *
1&
b11 C
#110000
0&
#115000
b11 >
b11 <
0(
1&
#120000
0&
#125000
b11 !
b11 =
1&
#130000
0&
#135000
b100 :
b100 <
1(
b100 '
b100 *
1&
b100 C
#140000
0&
#145000
b100 >
b101 <
0(
1&
#150000
0&
#155000
b101 >
b100 !
b100 =
1&
#160000
0&
#165000
1"
1&
#170000
0&
#175000
1&
#180000
0&
#185000
b0 <
0"
b0 !
b0 =
b0 :
b0 9
b0 8
b0 7
b0 >
1&
1)
#190000
0&
#195000
1&
#200000
0&
#205000
1&
0)
#210000
0&
#215000
1&
#220000
0&
#225000
b1 7
b1 <
1(
b1 '
b1 *
1&
b1 C
#230000
0&
#235000
b1 >
b1 <
0(
1&
#240000
0&
#245000
b1 !
b1 =
1&
#250000
0&
#255000
b10 8
b10 <
1(
b10 '
b10 *
1&
b10 C
#260000
0&
#265000
b10 >
b10 <
0(
1&
#270000
0&
#275000
b10 !
b10 =
1&
#280000
0&
#285000
b0 <
b0 !
b0 =
b0 8
b0 7
b0 >
1&
1)
#290000
0&
#295000
1&
#300000
0&
#305000
1&
0)
#310000
0&
#315000
1&
#320000
0&
#325000
b1 7
b1 <
1(
b1 '
b1 *
1&
b1 C
b101 B
#330000
0&
#335000
b1 >
b1 <
0(
1&
#340000
0&
#345000
b1 !
b1 =
1&
#350000
0&
#355000
b10 8
b10 <
1(
b10 '
b10 *
1&
b10 C
#360000
0&
#365000
b10 >
b10 <
0(
1&
#370000
0&
#375000
b10 !
b10 =
1&
#380000
0&
#385000
b11 9
b11 <
1(
b11 '
b11 *
1&
b11 C
#390000
0&
#395000
b11 >
b11 <
0(
1&
#400000
0&
#405000
b11 !
b11 =
1&
#410000
0&
#415000
b101 :
b100 <
1(
b101 '
b101 *
1&
b101 C
#420000
0&
#425000
b100 >
b110 <
0(
1&
#430000
0&
#435000
b0 <
b110 >
b100 !
b100 =
1&
#440000
0&
#445000
1$
b1 %
b1 ;
b0 >
1&
#450000
0&
b0 C
b0 B
b0 A
b0 @
b0 ?
#455000
b0 7
b0 !
b0 =
0$
b1 <
1(
b0 '
b0 *
1&
#460000
0&
#465000
b1 >
b1 <
0(
1&
#470000
0&
#475000
b1 !
b1 =
1&
#480000
0&
#485000
b0 8
b10 <
1(
1&
#490000
0&
#495000
b10 >
b10 <
0(
1&
#500000
0&
#505000
b10 !
b10 =
1&
#510000
0&
#515000
b0 9
b11 <
1(
1&
#520000
0&
#525000
b11 >
b11 <
0(
1&
#530000
0&
#535000
b11 !
b11 =
1&
#540000
0&
#545000
b0 :
b100 <
1(
1&
#550000
0&
#555000
b100 >
b110 <
0(
1&
#560000
0&
#565000
b0 <
b100 !
b100 =
b110 >
1&
#570000
0&
#575000
b0 >
b10 %
b10 ;
1$
1&
#580000
0&
#585000
b0 !
b0 =
0$
1&
#590000
0&
#595000
b1001 7
b1 <
1(
b1001 '
b1001 *
1&
b1001 C
b1001 B
b1001 A
b1001 @
b1001 ?
#600000
0&
#605000
b1 >
b1 <
0(
1&
#610000
0&
#615000
b1 !
b1 =
1&
#620000
0&
#625000
b1001 8
b10 <
1(
1&
#630000
0&
#635000
b10 >
b10 <
0(
1&
#640000
0&
#645000
b10 !
b10 =
1&
#650000
0&
#655000
b1001 9
b11 <
1(
1&
#660000
0&
#665000
b11 >
b11 <
0(
1&
#670000
0&
#675000
b11 !
b11 =
1&
#680000
0&
#685000
b1001 :
b100 <
1(
1&
#690000
0&
#695000
b100 >
b110 <
0(
1&
#700000
0&
#705000
b111 <
b100 !
b100 =
b110 >
1&
#710000
0&
#715000
b111 >
b11 %
b11 ;
1$
1&
#720000
0&
#725000
1#
0$
1&
#730000
0&
#735000
1(
b1 '
b1 *
1&
b1 C
#740000
0&
#745000
0(
1&
#750000
0&
#755000
1&
#760000
0&
#765000
b0 <
0#
b0 !
b0 =
b0 %
b0 ;
b0 :
b0 9
b0 8
b0 7
b0 >
1&
1)
#770000
0&
#775000
1&
#780000
0&
#785000
1&
0)
#790000
0&
#795000
1&
#800000
0&
#805000
b1 7
b1 <
1(
1&
b100 B
b11 A
b10 @
b1 ?
#810000
0&
#815000
b1 >
b1 <
0(
1&
#820000
0&
#825000
b1 !
b1 =
1&
#830000
0&
#835000
b10 8
b10 <
1(
b10 '
b10 *
1&
b10 C
#840000
0&
#845000
b10 >
b10 <
0(
1&
#850000
0&
#855000
b10 !
b10 =
1&
#860000
0&
#865000
b11 9
b11 <
1(
b11 '
b11 *
1&
b11 C
#870000
0&
#875000
b11 >
b11 <
0(
1&
#880000
0&
#885000
b11 !
b11 =
1&
#890000
0&
#895000
b100 :
b100 <
1(
b100 '
b100 *
1&
b100 C
#900000
0&
#905000
b100 >
b101 <
0(
1&
#910000
0&
#915000
b101 >
b100 !
b100 =
1&
#920000
0&
#925000
1"
1&
