digital_lock.v
module digital_lock (
    input  wire        clk,
    input  wire        rst,
    input  wire [3:0]  key_in,
    input  wire        key_valid,
    output reg  [3:0]  seg_digit,
    output reg         led_unlock,
    output reg         led_error,
    output reg         led_locked,
    output reg  [1:0]  error_count
);
// Module: digital_lock
// Description:
// - Receives four key presses (key_in, key_valid) and stores them as d0..d3
// - Compares the entered digits to the configured password (DIGIT0..DIGIT3)
// - On correct password, enters UNLOCKED state (led_unlock) for a duration, then returns to IDLE
// - On incorrect password, increments error_count; after three errors the system goes to LOCKED (led_locked)

// Interface:
// - clk        : clock input
// - rst        : synchronous reset (active high)
// - key_in     : 4-bit key value input
// - key_valid  : key valid pulse (one clock cycle per key press)
// - seg_digit  : indicates which digit is being entered (1..4) or status
// - led_unlock : unlock indicator
// - led_error  : error indicator
// - led_locked : locked indicator
// - error_count: number of errors (0..3)

// ========== Configurable password digits ==========
parameter DIGIT0 = 4'd1;
parameter DIGIT1 = 4'd2;
parameter DIGIT2 = 4'd3;
parameter DIGIT3 = 4'd4;

// ========== State encoding ==========
localparam IDLE      = 3'd0;
localparam INPUT_1   = 3'd1; // first digit entered
localparam INPUT_2   = 3'd2; // second digit entered
localparam INPUT_3   = 3'd3; // third digit entered
localparam CHECK     = 3'd4; // compare all four digits
localparam UNLOCKED  = 3'd5; // unlocked state
localparam ERROR     = 3'd6; // error state, increment error_count
localparam LOCKED    = 3'd7; // system locked

// State registers
reg [2:0] state, next_state;

// Storage for entered digits
reg [3:0] d0, d1, d2, d3;

// Unlock-state timer (clock cycles)
reg [7:0] unlock_timer;

// ====== 1) State register (clocked) ======
always @(posedge clk or posedge rst) begin
    if (rst)
        state <= IDLE;
    else
        state <= next_state;
end

// ====== 2) Next-state combinational logic ======
always @(*) begin
    case (state)
        IDLE:     next_state = key_valid ? INPUT_1 : IDLE;
        INPUT_1:  next_state = key_valid ? INPUT_2 : INPUT_1;
        INPUT_2:  next_state = key_valid ? INPUT_3 : INPUT_2;
        INPUT_3:  next_state = key_valid ? CHECK   : INPUT_3;
        CHECK: begin
            if ( (d0==DIGIT0)&&(d1==DIGIT1)&&(d2==DIGIT2)&&(d3==DIGIT3) )
                next_state = UNLOCKED; // correct password
            else
                next_state = ERROR;    // incorrect password
        end
        ERROR: begin
            // If error_count == 2 (this will be the 3rd error), go to LOCKED
            if (error_count == 2)
                next_state = LOCKED;
            else
                next_state = IDLE;
        end
        UNLOCKED: begin
            // Stay in UNLOCKED for a fixed number of clock cycles
            if (unlock_timer >= 20)
                next_state = IDLE;
            else
                next_state = UNLOCKED;
        end
        LOCKED:   next_state = LOCKED; // permanently locked
        default:  next_state = IDLE;
    endcase
end

// ====== 3) Outputs and internal updates (clocked) ======
always @(posedge clk or posedge rst) begin
    if (rst) begin
        // Reset outputs and internal storage
        seg_digit    <= 0;
        led_unlock   <= 0;
        led_error    <= 0;
        led_locked   <= 0;
        error_count  <= 0;
        d0<=0; d1<=0; d2<=0; d3<=0;
        unlock_timer <= 0;
    end else begin
        // Default values for this clock cycle
        led_error <= 0;

        case (state)
            IDLE: begin
                led_unlock   <= 0;
                led_locked   <= 0;
                seg_digit    <= 0;
                unlock_timer <= 0; // clear unlock timer when returning to IDLE
                if (key_valid) d0 <= key_in; // capture first digit on key press
            end

            INPUT_1: begin
                seg_digit <= 1; // indicate entering digit 1
                if (key_valid) d1 <= key_in;
            end

            INPUT_2: begin
                seg_digit <= 2; // indicate entering digit 2
                if (key_valid) d2 <= key_in;
            end

            INPUT_3: begin
                seg_digit <= 3; // indicate entering digit 3
                if (key_valid) d3 <= key_in;
            end

            CHECK: begin
                seg_digit <= 4; // indicate checking password
            end

            UNLOCKED: begin
                led_unlock   <= 1;                // show unlock
                unlock_timer <= unlock_timer + 1; // increment unlock timer
            end

            ERROR: begin
                led_error <= 1;                  // show error
                error_count <= error_count + 1;  // increment error count
            end

            LOCKED: begin
                led_locked <= 1; // show locked
            end
        endcase
    end
end

endmodule

tb_digital_lock.v
`timescale 1ns/1ps

module tb_digital_lock;

// 測試台：驗證 digital_lock 模組行為
// 測試內容：
// - 多組錯誤輸入以測試錯誤計數與鎖定
// - 正確輸入以測試解除功能
// - 重置行為測試

// ----- 信號宣告 -----
reg clk;            // 時脈 (10 ns 週期)
reg rst;            // 同步重置（高電位有效）
reg [3:0] key_in;   // 單鍵輸入
reg key_valid;      // 按鍵有效訊號

wire [3:0] seg_digit;
wire led_unlock;
wire led_error;
wire led_locked;
wire [1:0] error_count;

// ----- 被測模組 (DUT) 實體化 -----
digital_lock uut (
    .clk(clk),
    .rst(rst),
    .key_in(key_in),
    .key_valid(key_valid),
    .seg_digit(seg_digit),
    .led_unlock(led_unlock),
    .led_error(led_error),
    .led_locked(led_locked),
    .error_count(error_count)
);

// ----- 時脈產生：10ns 週期 -----
initial clk = 0;
always #5 clk = ~clk; 

// ----- Task：輸入四位密碼（依序按下 4 次） -----
task enter_password;
    input [3:0] d0,d1,d2,d3;
    begin
        press_key(d0);
        press_key(d1);
        press_key(d2);
        press_key(d3);
    end
endtask

// ----- Task：模擬按下一個按鍵 -----
task press_key;
    input [3:0] digit;
    begin
        @(posedge clk);
        key_in    = digit;
        key_valid = 1;
        @(posedge clk);
        key_valid = 0;
        #20; // 等待一些時間讓狀態轉移完成
    end
endtask

// ----- 測試流程 -----
initial begin
    // 啟動波形紀錄，方便後續檢視
    $dumpfile("wave.vcd"); 
    $dumpvars(0, tb_digital_lock); 

    // 初始值
    rst = 1; key_in = 0; key_valid = 0;
    #20; rst = 0;

    // 測試：連續三次錯誤輸入，檢查是否會鎖定
    $display("=== Error Input 1 ===");
    enter_password(9,9,9,9);
    #20; $display("time=%t unlock=%d, error=%d, locked=%d, count=%d", $time, led_unlock, led_error, led_locked, error_count);

    $display("=== Error Input 2 ===");
    enter_password(0,0,0,0);
    #20; $display("time=%t unlock=%d, error=%d, locked=%d, count=%d", $time, led_unlock, led_error, led_locked, error_count);

    $display("=== Error Input 3 ===");
    enter_password(1,1,1,1);
    #20; $display("time=%t unlock=%d, error=%d, locked=%d, count=%d", $time, led_unlock, led_error, led_locked, error_count);

    // 重置系統以測試重置後行為
    #50;
    $display(">>> System Reset <<<");
    rst = 1; #10; rst = 0;

    // 測試正確與錯誤交替輸入
    $display("=== Error Input 4 ===");
    enter_password(2,2,2,2);
    #20; $display("time=%t unlock=%d, error=%d, locked=%d, count=%d", $time, led_unlock, led_error, led_locked, error_count);

    $display("=== Correct Input 5 ===");
    enter_password(1,2,3,4);
    #20; $display("time=%t unlock=%d, error=%d, locked=%d, count=%d", $time, led_unlock, led_error, led_locked, error_count);

    $display("=== Error Input 6 ===");
    enter_password(3,3,3,3);
    #20; $display("time=%t unlock=%d, error=%d, locked=%d, count=%d", $time, led_unlock, led_error, led_locked, error_count);

    $display("=== Error Input 7 ===");
    enter_password(4,4,4,4);
    #20; $display("time=%t unlock=%d, error=%d, locked=%d, count=%d", $time, led_unlock, led_error, led_locked, error_count);

    $display("=== Correct Input 8 ===");
    enter_password(1,2,3,4);
    #20; $display("time=%t unlock=%d, error=%d, locked=%d, count=%d", $time, led_unlock, led_error, led_locked, error_count);

    $display("=== Error Input 9 ===");
    enter_password(7,7,7,7);
    #20; $display("time=%t unlock=%d, error=%d, locked=%d, count=%d", $time, led_unlock, led_error, led_locked, error_count);

    $display("=== Correct Input 10 ===");
    enter_password(1,2,3,4);
    #20; $display("time=%t unlock=%d, error=%d, locked=%d, count=%d", $time, led_unlock, led_error, led_locked, error_count);

    #50;
    $finish; // 結束模擬
end

endmodule

wave.vcd
$date
	Sun May 24 22:34:11 2026
$end
$version
	Icarus Verilog
$end
$timescale
	1ps
$end
$scope module tb_digital_lock $end
$var wire 4 ! seg_digit [3:0] $end
$var wire 1 " led_unlock $end
$var wire 1 # led_locked $end
$var wire 1 $ led_error $end
$var wire 2 % error_count [1:0] $end
$var reg 1 & clk $end
$var reg 4 ' key_in [3:0] $end
$var reg 1 ( key_valid $end
$var reg 1 ) rst $end
$scope module uut $end
$var wire 1 & clk $end
$var wire 4 * key_in [3:0] $end
$var wire 1 ( key_valid $end
$var wire 1 ) rst $end
$var parameter 3 + CHECK $end
$var parameter 4 , DIGIT0 $end
$var parameter 4 - DIGIT1 $end
$var parameter 4 . DIGIT2 $end
$var parameter 4 / DIGIT3 $end
$var parameter 3 0 ERROR $end
$var parameter 3 1 IDLE $end
$var parameter 3 2 INPUT_1 $end
$var parameter 3 3 INPUT_2 $end
$var parameter 3 4 INPUT_3 $end
$var parameter 3 5 LOCKED $end
$var parameter 3 6 UNLOCKED $end
$var reg 4 7 d0 [3:0] $end
$var reg 4 8 d1 [3:0] $end
$var reg 4 9 d2 [3:0] $end
$var reg 4 : d3 [3:0] $end
$var reg 2 ; error_count [1:0] $end
$var reg 1 $ led_error $end
$var reg 1 # led_locked $end
$var reg 1 " led_unlock $end
$var reg 3 < next_state [2:0] $end
$var reg 4 = seg_digit [3:0] $end
$var reg 3 > state [2:0] $end
$var reg 8 ? unlock_timer [7:0] $end
$upscope $end
$scope task enter_password $end
$var reg 4 @ d0 [3:0] $end
$var reg 4 A d1 [3:0] $end
$var reg 4 B d2 [3:0] $end
$var reg 4 C d3 [3:0] $end
$upscope $end
$scope task press_key $end
$var reg 4 D digit [3:0] $end
$upscope $end
$upscope $end
$enddefinitions $end
$comment Show the parameter values. $end
$dumpall
b101 6
b111 5
b11 4
b10 3
b1 2
b0 1
b110 0
b100 /
b11 .
b10 -
b1 ,
b100 +
$end
#0
$dumpvars
bx D
bx C
bx B
bx A
bx @
b0 ?
b0 >
b0 =
b0 <
b0 ;
b0 :
b0 9
b0 8
b0 7
b0 *
1)
0(
b0 '
0&
b0 %
0$
0#
0"
b0 !
$end
#5000
1&
#10000
0&
#15000
1&
#20000
0&
b1001 D
b1001 C
b1001 B
b1001 A
b1001 @
0)
#25000
b1001 7
b1 <
1(
b1001 '
b1001 *
1&
#30000
0&
#35000
b1 >
b1 <
0(
1&
#40000
0&
#45000
b1 !
b1 =
1&
#50000
0&
#55000
b1001 8
b10 <
1(
1&
#60000
0&
#65000
b10 >
b10 <
0(
1&
#70000
0&
#75000
b10 !
b10 =
1&
#80000
0&
#85000
b1001 9
b11 <
1(
1&
#90000
0&
#95000
b11 >
b11 <
0(
1&
#100000
0&
#105000
b11 !
b11 =
1&
#110000
0&
#115000
b1001 :
b100 <
1(
1&
#120000
0&
#125000
b100 >
b110 <
0(
1&
#130000
0&
#135000
b0 <
b110 >
b100 !
b100 =
1&
#140000
0&
#145000
b1 %
b1 ;
1$
b0 >
1&
#150000
0&
#155000
b0 !
b0 =
0$
1&
#160000
0&
#165000
b0 7
b1 <
1(
b0 '
b0 *
1&
b0 D
b0 C
b0 B
b0 A
b0 @
#170000
0&
#175000
b1 >
b1 <
0(
1&
#180000
0&
#185000
b1 !
b1 =
1&
#190000
0&
#195000
b0 8
b10 <
1(
1&
#200000
0&
#205000
b10 >
b10 <
0(
1&
#210000
0&
#215000
b10 !
b10 =
1&
#220000
0&
#225000
b0 9
b11 <
1(
1&
#230000
0&
#235000
b11 >
b11 <
0(
1&
#240000
0&
#245000
b11 !
b11 =
1&
#250000
0&
#255000
b0 :
b100 <
1(
1&
#260000
0&
#265000
b100 >
b110 <
0(
1&
#270000
0&
#275000
b0 <
b110 >
b100 !
b100 =
1&
#280000
0&
#285000
b10 %
b10 ;
1$
b0 >
1&
#290000
0&
#295000
b0 !
b0 =
0$
1&
#300000
0&
#305000
b1 7
b1 <
1(
b1 '
b1 *
1&
b1 D
b1 C
b1 B
b1 A
b1 @
#310000
0&
#315000
b1 >
b1 <
0(
1&
#320000
0&
#325000
b1 !
b1 =
1&
#330000
0&
#335000
b1 8
b10 <
1(
1&
#340000
0&
#345000
b10 >
b10 <
0(
1&
#350000
0&
#355000
b10 !
b10 =
1&
#360000
0&
#365000
b1 9
b11 <
1(
1&
#370000
0&
#375000
b11 >
b11 <
0(
1&
#380000
0&
#385000
b11 !
b11 =
1&
#390000
0&
#395000
b1 :
b100 <
1(
1&
#400000
0&
#405000
b100 >
b110 <
0(
1&
#410000
0&
#415000
b111 <
b110 >
b100 !
b100 =
1&
#420000
0&
#425000
b11 %
b11 ;
1$
b111 >
1&
#430000
0&
#435000
1#
0$
1&
#440000
0&
#445000
1&
#450000
0&
#455000
1&
#460000
0&
#465000
1&
#470000
0&
#475000
1&
#480000
0&
#485000
1&
#490000
0&
#495000
b0 <
b0 >
b0 :
b0 9
b0 8
b0 7
b0 %
b0 ;
0#
b0 !
b0 =
1&
1)
#500000
0&
#505000
b10 7
b1 <
1(
b10 '
b10 *
1&
b10 D
b10 C
b10 B
b10 A
b10 @
0)
#510000
0&
#515000
b1 >
b1 <
0(
1&
#520000
0&
#525000
b1 !
b1 =
1&
#530000
0&
#535000
b10 8
b10 <
1(
1&
#540000
0&
#545000
b10 >
b10 <
0(
1&
#550000
0&
#555000
b10 !
b10 =
1&
#560000
0&
#565000
b10 9
b11 <
1(
1&
#570000
0&
#575000
b11 >
b11 <
0(
1&
#580000
0&
#585000
b11 !
b11 =
1&
#590000
0&
#595000
b10 :
b100 <
1(
1&
#600000
0&
#605000
b100 >
b110 <
0(
1&
#610000
0&
#615000
b0 <
b110 >
b100 !
b100 =
1&
#620000
0&
#625000
b1 %
b1 ;
1$
b0 >
1&
#630000
0&
#635000
b0 !
b0 =
0$
1&
#640000
0&
#645000
b1 7
b1 <
1(
b1 '
b1 *
1&
b1 D
b100 C
b11 B
b1 @
#650000
0&
#655000
b1 >
b1 <
0(
1&
#660000
0&
#665000
b1 !
b1 =
1&
#670000
0&
#675000
b10 <
1(
b10 '
b10 *
1&
b10 D
#680000
0&
#685000
b10 >
b10 <
0(
1&
#690000
0&
#695000
b10 !
b10 =
1&
#700000
0&
#705000
b11 9
b11 <
1(
b11 '
b11 *
1&
b11 D
#710000
0&
#715000
b11 >
b11 <
0(
1&
#720000
0&
#725000
b11 !
b11 =
1&
#730000
0&
#735000
b100 :
b100 <
1(
b100 '
b100 *
1&
b100 D
#740000
0&
#745000
b100 >
b101 <
0(
1&
#750000
0&
#755000
b101 >
b100 !
b100 =
1&
#760000
0&
#765000
b1 ?
1"
1&
#770000
0&
#775000
b10 ?
1&
#780000
0&
#785000
b11 ?
1(
b11 '
b11 *
1&
b11 D
b11 C
b11 A
b11 @
#790000
0&
#795000
b100 ?
0(
1&
#800000
0&
#805000
b101 ?
1&
#810000
0&
#815000
b110 ?
1(
1&
#820000
0&
#825000
b111 ?
0(
1&
#830000
0&
#835000
b1000 ?
1&
#840000
0&
#845000
b1001 ?
1(
1&
#850000
0&
#855000
b1010 ?
0(
1&
#860000
0&
#865000
b1011 ?
1&
#870000
0&
#875000
b1100 ?
1(
1&
#880000
0&
#885000
b1101 ?
0(
1&
#890000
0&
#895000
b1110 ?
1&
#900000
0&
#905000
b1111 ?
1&
#910000
0&
#915000
b10000 ?
1&
#920000
0&
#925000
b10001 ?
1(
b100 '
b100 *
1&
b100 D
b100 C
b100 B
b100 A
b100 @
#930000
0&
#935000
b10010 ?
0(
1&
#940000
0&
#945000
b10011 ?
1&
#950000
0&
#955000
b0 <
b10100 ?
1(
1&
#960000
0&
#965000
b10101 ?
b0 >
0(
1&
#970000
0&
#975000
b0 ?
b0 !
b0 =
0"
1&
#980000
0&
#985000
b100 7
b1 <
1(
1&
#990000
0&
#995000
b1 >
b1 <
0(
1&
#1000000
0&
#1005000
b1 !
b1 =
1&
#1010000
0&
#1015000
b100 8
b10 <
1(
1&
#1020000
0&
#1025000
b10 >
b10 <
0(
1&
#1030000
0&
#1035000
b10 !
b10 =
1&
#1040000
0&
#1045000
1&
#1050000
0&
#1055000
1&
#1060000
0&
#1065000
b1 9
b11 <
1(
b1 '
b1 *
1&
b1 D
b11 B
b10 A
b1 @
#1070000
0&
#1075000
b11 >
b11 <
0(
1&
#1080000
0&
#1085000
b11 !
b11 =
1&
#1090000
0&
#1095000
b10 :
b100 <
1(
b10 '
b10 *
1&
b10 D
#1100000
0&
#1105000
b100 >
b110 <
0(
1&
#1110000
0&
#1115000
b0 <
b110 >
b100 !
b100 =
1&
#1120000
0&
#1125000
b1 <
b10 %
b10 ;
1$
b0 >
1(
b11 '
b11 *
1&
b11 D
#1130000
0&
#1135000
b1 >
b0 !
b0 =
0$
b1 <
0(
1&
#1140000
0&
#1145000
b1 !
b1 =
1&
#1150000
0&
#1155000
b10 <
1(
b100 '
b100 *
1&
b100 D
#1160000
0&
#1165000
b10 >
b10 <
0(
1&
#1170000
0&
#1175000
b10 !
b10 =
1&
#1180000
0&
#1185000
1&
#1190000
0&
#1195000
1&
#1200000
0&
#1205000
b111 9
b11 <
1(
b111 '
b111 *
1&
b111 D
b111 C
b111 B
b111 A
b111 @
#1210000
0&
#1215000
b11 >
b11 <
0(
1&
#1220000
0&
#1225000
b11 !
b11 =
1&
#1230000
0&
#1235000
b111 :
b100 <
1(
1&
#1240000
0&
#1245000
b100 >
b110 <
0(
1&
#1250000
0&
#1255000
b111 <
b110 >
b100 !
b100 =
1&
#1260000
0&
#1265000
b11 %
b11 ;
1$
b111 >
1(
1&
#1270000
0&
#1275000
1#
0$
0(
1&
#1280000
0&
#1285000
1&
#1290000
0&
#1295000
1(
1&
#1300000
0&
#1305000
0(
1&
#1310000
0&
#1315000
1&
#1320000
0&
#1325000
1&
#1330000
0&
#1335000
1&
#1340000
0&
#1345000
1(
b1 '
b1 *
1&
b1 D
b100 C
b11 B
b10 A
b1 @
#1350000
0&
#1355000
0(
1&
#1360000
0&
#1365000
1&
#1370000
0&
#1375000
1(
b10 '
b10 *
1&
b10 D
#1380000
0&
#1385000
0(
1&
#1390000
0&
#1395000
1&
#1400000
0&
#1405000
1(
b11 '
b11 *
1&
b11 D
#1410000
0&
#1415000
0(
1&
#1420000
0&
#1425000
1&
#1430000
0&
#1435000
1(
b100 '
b100 *
1&
b100 D
#1440000
0&
#1445000
0(
1&
