digital_lock.v
module digital_lock (
    input  wire        clk,          // 系統時脈
    input  wire        rst,          // 非同步重置（高電位有效）
    input  wire [3:0]  key_in,       // 使用者輸入數字 (0-9)
    input  wire        key_valid,    // 輸入有效脈衝
    output reg  [3:0]  seg_digit,    // 當前已輸入位數 (0-4)
    output reg         led_unlock,   // 解鎖成功指示燈
    output reg         led_error,    // 輸入錯誤指示燈（維持一拍）
    output reg         led_locked,   // 系統鎖定指示燈（連續三次錯誤）
    output reg  [1:0]  error_count   // 當前累計錯誤次數
);

// ========== 可配置密碼位數 (預設密碼 1-2-3-4) ==========
parameter DIGIT0 = 4'd1;
parameter DIGIT1 = 4'd2;
parameter DIGIT2 = 4'd3;
parameter DIGIT3 = 4'd4;

/*new*/
//超過此時間回到IDLE(為方便波形測試設成較小的數)
parameter TIMEOUT_MAX = 5'd20;

// ========== 有限狀態機 (FSM) 狀態編碼 ==========
localparam IDLE      = 3'd0; // 等待第 1 位
localparam INPUT_1   = 3'd1; // 已收第 1 位，等待第 2 位
localparam INPUT_2   = 3'd2; // 已收第 2 位，等待第 3 位
localparam INPUT_3   = 3'd3; // 已收第 3 位，等待第 4 位
localparam CHECK     = 3'd4; // 密碼比對狀態
localparam UNLOCKED  = 3'd5; // 解鎖成功狀態
localparam ERROR     = 3'd6; // 密碼錯誤狀態
localparam LOCKED    = 3'd7; // 系統鎖定狀態

// 狀態暫存器
reg [2:0] state, next_state;

// 儲存輸入數字的暫存器
reg [3:0] d0, d1, d2, d3;

/*new*/
//計時器
reg [4:0] timeout_counter;

// ====== 1) 狀態暫存器 (序向邏輯) ======
// 處理狀態轉換與系統重置
always @(posedge clk or posedge rst) begin
    if (rst)
        state <= IDLE;
    else
        state <= next_state;
end

// ====== 2) 次態邏輯 (組合邏輯) ======
// 根據當前狀態與輸入條件判斷下一個狀態
always @(*) begin
    next_state = state; // 預設保持當前狀態
    case (state)
        IDLE: begin
            // 收到有效數字且在 0-9 範圍內，進入下一個輸入階段
            if (key_valid && key_in <= 4'd9)
                next_state = INPUT_1;
            else
                next_state = IDLE;
        end
        INPUT_1: begin
            if (key_valid && key_in <= 4'd9)
                next_state = INPUT_2;
            /*new*/
            else if(timeout_counter >= TIMEOUT_MAX)
                next_state = IDLE;
            else
                next_state = INPUT_1;
        end
        INPUT_2: begin
            if (key_valid && key_in <= 4'd9)
                next_state = INPUT_3;
            /*new*/
            else if(timeout_counter >= TIMEOUT_MAX)
                next_state = IDLE;
            else
                next_state = INPUT_2;
        end
        INPUT_3: begin
            if (key_valid && key_in <= 4'd9)
                next_state = CHECK;
            /*new*/
            else if(timeout_counter >= TIMEOUT_MAX)
                next_state = IDLE;
            else
                next_state = INPUT_3;
        end
        CHECK: begin
            // 比對四位數暫存器與預設密碼是否全等
            if ( (d0 == DIGIT0) && (d1 == DIGIT1) && (d2 == DIGIT2) && (d3 == DIGIT3) )
                next_state = UNLOCKED;
            else
                next_state = ERROR;
        end
        ERROR: begin
            // 判斷錯誤次數是否已達上限 (第 3 次錯誤後鎖定)
            if (error_count >= 2'd2) 
                next_state = LOCKED;
            else
                next_state = IDLE;
        end
        UNLOCKED: begin
            // 解鎖後保持在該狀態，直到按下重置
            next_state = UNLOCKED;
        end
        LOCKED: begin
            // 鎖定後拒絕任何輸入，直到按下重置
            next_state = LOCKED;
            seg_digit = 4'd0;
        end
        default: next_state = IDLE;
    endcase
end

// ====== 3) 內部資料儲存與錯誤計數 (序向邏輯) ======
// 負責存儲输入的密碼與維護錯誤計數器
always @(posedge clk or posedge rst) begin
    if (rst) begin
        d0 <= 4'd0;
        d1 <= 4'd0;
        d2 <= 4'd0;
        d3 <= 4'd0;
        error_count <= 2'd0;
    end else begin
        case (state)
            IDLE: begin
                if (key_valid && key_in <= 4'd9)
                    d0 <= key_in;
            end
            INPUT_1: begin
                if (key_valid && key_in <= 4'd9)
                    d1 <= key_in;
            end
            INPUT_2: begin
                if (key_valid && key_in <= 4'd9)
                    d2 <= key_in;
            end
            INPUT_3: begin
                if (key_valid && key_in <= 4'd9)
                    d3 <= key_in;
            end
            CHECK: begin
                // 如果密碼正確，清除錯誤計數。若錯誤，則由 ERROR 狀態處理遞增。
                if ( (d0 == DIGIT0) && (d1 == DIGIT1) && (d2 == DIGIT2) && (d3 == DIGIT3) )
                    error_count <= 2'd0;
            end
            ERROR: begin
                // 進入錯誤狀態時遞增計數器
                if (error_count < 2'd3)
                    error_count <= error_count + 2'd1;
            end
            default: ;
        endcase
    end
end

// ====== 4) 輸出邏輯 (序向邏輯) ======
// 採用 Moore FSM 風格，根據當前狀態驅動各項輸出指示
always @(posedge clk or posedge rst) begin
    if (rst) begin
        seg_digit    <= 4'd0;
        led_unlock   <= 1'b0;
        led_error    <= 1'b0;
        led_locked   <= 1'b0;
    end else begin
        // 預設將錯誤燈熄滅，確保它只亮起一拍
        led_error <= 1'b0;
        
        case (state)
            IDLE: begin
                seg_digit    <= 4'd0;
                led_unlock   <= 1'b0;
                led_locked   <= 1'b0;
            end
            INPUT_1: begin
                seg_digit <= 4'd1;
            end
            INPUT_2: begin
                seg_digit <= 4'd2;
            end
            INPUT_3: begin
                seg_digit <= 4'd3;
            end
            CHECK: begin
                seg_digit <= 4'd4;
            end
            UNLOCKED: begin
                led_unlock <= 1'b1;
            end
            ERROR: begin
                led_error <= 1'b1;
            end
            LOCKED: begin
                led_locked <= 1'b1;
                seg_digit <= 4'd0;
            end
        endcase
    end
end

/*new*/
/*timer計時*/
always @(posedge clk or posedge rst) begin
    if(rst) begin
        timeout_counter <= 32'd0;
    end
    else begin
        if(state == IDLE)
            timeout_counter <= 32'd0;
        else if(key_valid)
            timeout_counter <= 32'd0;
        else
            timeout_counter <= timeout_counter + 32'd1;
    end
end

endmodule

tb_digital_lock.v
`timescale 1ns/1ps

module tb_digital_lock;

// --- 信號宣告 ---
reg clk;
reg rst;
reg [3:0] key_in;
reg key_valid;

wire [3:0] seg_digit;
wire led_unlock;
wire led_error;
wire led_locked;
wire [1:0] error_count;

// --- 待測物 (DUT) 實體化 ---
digital_lock uut (
    .clk(clk),
    .rst(rst),
    .key_in(key_in),
    .key_valid(key_valid),
    .seg_digit(seg_digit),
    .led_unlock(led_unlock),
    .led_error(led_error),
    .led_locked(led_locked),
    .error_count(error_count)
);

// --- 時脈產生 (100MHz，週期 10ns) ---
initial clk = 0;
always #5 clk = ~clk;

// --- 模擬按鍵輸入的任務 (Task) ---
// 模擬按下按鍵後，key_valid 產生一個時脈週期的脈衝
task press_key;
    input [3:0] digit;
    begin
        @(posedge clk);
        key_in = digit;
        key_valid = 1'b1;
        @(posedge clk);
        key_valid = 1'b0;
        #20; // 模擬按鍵去彈跳 (Debounce) 的時間間隔
    end
endtask

// --- 輸入四位密碼的任務 (Task) ---
task enter_password;
    input [3:0] d0, d1, d2, d3;
    begin
        press_key(d0);
        press_key(d1);
        press_key(d2);
        press_key(d3);
    end
endtask

// --- 測試流程 ---
initial begin
    // 開啟波形檔案紀錄
    $dumpfile("wave.vcd");
    $dumpvars(0, tb_digital_lock);

    // 系統初始化與非同步重置
    rst = 1; key_in = 0; key_valid = 0;
    #25; rst = 0;
    #20;

    // --- 測試情境 1: 正確密碼測試 (1->2->3->4) ---
    $display("=== Scenario 1: Correct Password (1-2-3-4) ===");
    enter_password(4'd1, 4'd2, 4'd3, 4'd4);
    #20;
    $display("Time=%t | led_unlock=%b, led_error=%b, led_locked=%b, seg_digit=%d", $time, led_unlock, led_error, led_locked, seg_digit);
    
    if (led_unlock) $display(">>> SUCCESS: System Unlocked");
    else $display(">>> FAILURE: System failed to unlock");

    // --- 測試情境 5: 中途重置測試 (輸入到一半按 rst) ---
    $display("\n>>> Resetting system...");
    rst = 1; #20; rst = 0; #20;
    $display("=== Scenario 5: Mid-input Reset ===");
    press_key(4'd1);
    press_key(4'd2);
    $display("Before reset: seg_digit=%d", seg_digit);
    rst = 1; #20; rst = 0; #20;
    $display("After reset:  seg_digit=%d", seg_digit);

    if (seg_digit == 0) $display(">>> SUCCESS: seg_digit reset to 0");
    else $display(">>> FAILURE: seg_digit not reset");

    // --- 測試情境 2: 單次錯誤測試 (1->2->3->5，最後一位錯誤) ---
    $display("\n=== Scenario 2: Single Error (1-2-3-5) ===");
    enter_password(4'd1, 4'd2, 4'd3, 4'd5);
    #5; // 稍微等待以捕捉 led_error 的一拍脈衝
    $display("Time=%t | led_unlock=%b, led_error=%b, led_locked=%b, error_count=%d", $time, led_unlock, led_error, led_locked, error_count);
    if (error_count == 1) $display(">>> SUCCESS: error_count incremented to 1");
    else $display(">>> FAILURE: error_count is %d", error_count);

    /*// --- 測試情境 3: 連續三次錯誤鎖定測試 ---
    $display("\n=== Scenario 3: Three Errors Lockout ===");
    // 目前已有 1 次錯誤 (由測試 2 產生)
    // 進行第 2 次錯誤輸入
    $display("Entering 2nd wrong password...");
    enter_password(4'd0, 4'd0, 4'd0, 4'd0);
    #20;
    // 進行第 3 次錯誤輸入
    $display("Entering 3rd wrong password...");
    enter_password(4'd9, 4'd9, 4'd9, 4'd9);
    #20;
    $display("Time=%t | led_unlock=%b, led_error=%b, led_locked=%b, error_count=%d", $time, led_unlock, led_error, led_locked, error_count);
    if (led_locked) $display(">>> SUCCESS: System Locked");
    else $display(">>> FAILURE: System not locked");*/

    /*// --- 測試情境 4: 鎖定後重置測試 ---
    $display("\n=== Scenario 4: Reset after Locked ===");
    $display("Trying to enter key while locked (expected ignore)...");
    press_key(4'd1);
    if (seg_digit == 0) $display("Key ignored as expected");
    
    $display("resetting...");
    rst = 1; #20; rst = 0; #20;
    $display("After reset: led_locked=%b, error_count=%d, seg_digit=%d", led_locked, error_count, seg_digit);
    
    $display("After reset, entering correct password...");
    enter_password(4'd1, 4'd2, 4'd3, 4'd4);
    #20;
    $display("Time=%t | led_unlock=%b, led_error=%b, led_locked=%b, error_count=%d", $time, led_unlock, led_error, led_locked, error_count);
    if (led_unlock) $display(">>> SUCCESS: System Unlocked after reset");
    else $display(">>> FAILURE: System failed to unlock after reset");*/

    /*new*/
    //--- 測試情境 6: 輸入超時 ---
    $monitor("Time=%t | seg_digit=%d, led_locked=%b, error_count=%d", $time, seg_digit, led_locked, error_count);
    $display("\n=== Scenario 6: Timeout ===");
	 rst = 1; #20; rst = 0; #20;
    
    enter_password(4'd1, 4'd2, 4'd3, 4'd5);
    press_key(4'd1);
    
    #205;
    
    #100;
    $finish; // 結束模擬
end

endmodule

wave.vcd
$date
	Thu May 28 16:30:12 2026
$end
$version
	Icarus Verilog
$end
$timescale
	1ps
$end
$scope module tb_digital_lock $end
$var wire 4 ! seg_digit [3:0] $end
$var wire 1 " led_unlock $end
$var wire 1 # led_locked $end
$var wire 1 $ led_error $end
$var wire 2 % error_count [1:0] $end
$var reg 1 & clk $end
$var reg 4 ' key_in [3:0] $end
$var reg 1 ( key_valid $end
$var reg 1 ) rst $end
$scope module uut $end
$var wire 1 & clk $end
$var wire 4 * key_in [3:0] $end
$var wire 1 ( key_valid $end
$var wire 1 ) rst $end
$var parameter 3 + CHECK $end
$var parameter 4 , DIGIT0 $end
$var parameter 4 - DIGIT1 $end
$var parameter 4 . DIGIT2 $end
$var parameter 4 / DIGIT3 $end
$var parameter 3 0 ERROR $end
$var parameter 3 1 IDLE $end
$var parameter 3 2 INPUT_1 $end
$var parameter 3 3 INPUT_2 $end
$var parameter 3 4 INPUT_3 $end
$var parameter 3 5 LOCKED $end
$var parameter 5 6 TIMEOUT_MAX $end
$var parameter 3 7 UNLOCKED $end
$var reg 4 8 d0 [3:0] $end
$var reg 4 9 d1 [3:0] $end
$var reg 4 : d2 [3:0] $end
$var reg 4 ; d3 [3:0] $end
$var reg 2 < error_count [1:0] $end
$var reg 1 $ led_error $end
$var reg 1 # led_locked $end
$var reg 1 " led_unlock $end
$var reg 3 = next_state [2:0] $end
$var reg 4 > seg_digit [3:0] $end
$var reg 3 ? state [2:0] $end
$var reg 5 @ timeout_counter [4:0] $end
$upscope $end
$scope task enter_password $end
$var reg 4 A d0 [3:0] $end
$var reg 4 B d1 [3:0] $end
$var reg 4 C d2 [3:0] $end
$var reg 4 D d3 [3:0] $end
$upscope $end
$scope task press_key $end
$var reg 4 E digit [3:0] $end
$upscope $end
$upscope $end
$enddefinitions $end
$comment Show the parameter values. $end
$dumpall
b101 7
b10100 6
b111 5
b11 4
b10 3
b1 2
b0 1
b110 0
b100 /
b11 .
b10 -
b1 ,
b100 +
$end
#0
$dumpvars
bx E
bx D
bx C
bx B
bx A
b0 @
b0 ?
b0 >
b0 =
b0 <
b0 ;
b0 :
b0 9
b0 8
b0 *
1)
0(
b0 '
0&
b0 %
0$
0#
0"
b0 !
$end
#5000
1&
#10000
0&
#15000
1&
#20000
0&
#25000
1&
0)
#30000
0&
#35000
1&
#40000
0&
#45000
b1 8
b1 =
1(
b1 '
b1 *
1&
b1 E
b100 D
b11 C
b10 B
b1 A
#50000
0&
#55000
b1 ?
b1 =
0(
1&
#60000
0&
#65000
b1 @
b1 !
b1 >
1&
#70000
0&
#75000
b10 9
b0 @
b10 =
1(
b10 '
b10 *
1&
b10 E
#80000
0&
#85000
b1 @
b10 ?
b10 =
0(
1&
#90000
0&
#95000
b10 !
b10 >
b10 @
1&
#100000
0&
#105000
b0 @
b11 :
b11 =
1(
b11 '
b11 *
1&
b11 E
#110000
0&
#115000
b11 ?
b1 @
b11 =
0(
1&
#120000
0&
#125000
b10 @
b11 !
b11 >
1&
#130000
0&
#135000
b100 ;
b0 @
b100 =
1(
b100 '
b100 *
1&
b100 E
#140000
0&
#145000
b1 @
b100 ?
b101 =
0(
1&
#150000
0&
#155000
b101 ?
b100 !
b100 >
b10 @
1&
#160000
0&
#165000
b11 @
1"
1&
#170000
0&
#175000
b100 @
1&
#180000
0&
#185000
b0 =
b0 @
0"
b0 !
b0 >
b0 ;
b0 :
b0 9
b0 8
b0 ?
1&
1)
#190000
0&
#195000
1&
#200000
0&
#205000
1&
0)
#210000
0&
#215000
1&
#220000
0&
#225000
b1 8
b1 =
1(
b1 '
b1 *
1&
b1 E
#230000
0&
#235000
b1 ?
b1 =
0(
1&
#240000
0&
#245000
b1 @
b1 !
b1 >
1&
#250000
0&
#255000
b10 9
b0 @
b10 =
1(
b10 '
b10 *
1&
b10 E
#260000
0&
#265000
b1 @
b10 ?
b10 =
0(
1&
#270000
0&
#275000
b10 !
b10 >
b10 @
1&
#280000
0&
#285000
b0 =
b0 @
b0 !
b0 >
b0 9
b0 8
b0 ?
1&
1)
#290000
0&
#295000
1&
#300000
0&
#305000
1&
0)
#310000
0&
#315000
1&
#320000
0&
#325000
b1 8
b1 =
1(
b1 '
b1 *
1&
b1 E
b101 D
#330000
0&
#335000
b1 ?
b1 =
0(
1&
#340000
0&
#345000
b1 @
b1 !
b1 >
1&
#350000
0&
#355000
b10 9
b0 @
b10 =
1(
b10 '
b10 *
1&
b10 E
#360000
0&
#365000
b1 @
b10 ?
b10 =
0(
1&
#370000
0&
#375000
b10 !
b10 >
b10 @
1&
#380000
0&
#385000
b0 @
b11 :
b11 =
1(
b11 '
b11 *
1&
b11 E
#390000
0&
#395000
b11 ?
b1 @
b11 =
0(
1&
#400000
0&
#405000
b10 @
b11 !
b11 >
1&
#410000
0&
#415000
b101 ;
b0 @
b100 =
1(
b101 '
b101 *
1&
b101 E
#420000
0&
#425000
b1 @
b100 ?
b110 =
0(
1&
#430000
0&
#435000
b0 =
b110 ?
b100 !
b100 >
b10 @
1&
#440000
0&
#445000
b11 @
1$
b1 %
b1 <
b0 ?
1&
#450000
b0 %
b0 <
b0 ;
b0 :
b0 9
b0 8
0$
b0 !
b0 >
b0 @
0&
1)
#455000
1&
#460000
0&
#465000
1&
#470000
0&
0)
#475000
1&
#480000
0&
#485000
1&
#490000
0&
b1 E
#495000
b1 8
b1 =
1(
b1 '
b1 *
1&
#500000
0&
#505000
b1 ?
b1 =
0(
1&
#510000
0&
#515000
b1 @
b1 !
b1 >
1&
#520000
0&
#525000
b10 9
b0 @
b10 =
1(
b10 '
b10 *
1&
b10 E
#530000
0&
#535000
b1 @
b10 ?
b10 =
0(
1&
#540000
0&
#545000
b10 !
b10 >
b10 @
1&
#550000
0&
#555000
b0 @
b11 :
b11 =
1(
b11 '
b11 *
1&
b11 E
#560000
0&
#565000
b11 ?
b1 @
b11 =
0(
1&
#570000
0&
#575000
b10 @
b11 !
b11 >
1&
#580000
0&
#585000
b101 ;
b0 @
b100 =
1(
b101 '
b101 *
1&
b101 E
#590000
0&
#595000
b1 @
b100 ?
b110 =
0(
1&
#600000
0&
#605000
b0 =
b110 ?
b100 !
b100 >
b10 @
1&
#610000
0&
#615000
b0 @
1$
b1 %
b1 <
b0 ?
b1 =
1(
b1 '
b1 *
1&
b1 E
#620000
0&
#625000
b1 ?
b0 !
b0 >
0$
b1 =
0(
1&
#630000
0&
#635000
b1 @
b1 !
b1 >
1&
#640000
0&
#645000
b10 @
1&
#650000
0&
#655000
b11 @
1&
#660000
0&
#665000
b100 @
1&
#670000
0&
#675000
b101 @
1&
#680000
0&
#685000
b110 @
1&
#690000
0&
#695000
b111 @
1&
#700000
0&
#705000
b1000 @
1&
#710000
0&
#715000
b1001 @
1&
#720000
0&
#725000
b1010 @
1&
#730000
0&
#735000
b1011 @
1&
#740000
0&
#745000
b1100 @
1&
#750000
0&
#755000
b1101 @
1&
#760000
0&
#765000
b1110 @
1&
#770000
0&
#775000
b1111 @
1&
#780000
0&
#785000
b10000 @
1&
#790000
0&
#795000
b10001 @
1&
#800000
0&
#805000
b10010 @
1&
#810000
0&
#815000
b10011 @
1&
#820000
0&
#825000
b0 =
b10100 @
1&
#830000
0&
#835000
b10101 @
b0 ?
1&
#840000
0&
#845000
b0 !
b0 >
b0 @
1&
